README
setup.py
tests.py
twitterator.py
twitterator.egg-info/PKG-INFO
twitterator.egg-info/SOURCES.txt
twitterator.egg-info/dependency_links.txt
twitterator.egg-info/top_level.txt