Metadata-Version: 1.1
Name: twitterator
Version: 0.2
Summary: iterating functions for twitter api
Home-page: http://python.org/pypi/twitterator
Author: Ed Summers
Author-email: ehs@pobox.com
License: http://creativecommons.org/licenses/publicdomain/
Platform: UNKNOWN
Requires: httplib2
